LICENSE
README.md
reditio.py
setup.py
reditio.egg-info/PKG-INFO
reditio.egg-info/SOURCES.txt
reditio.egg-info/dependency_links.txt
reditio.egg-info/requires.txt
reditio.egg-info/top_level.txt