Metadata-Version: 2.1
Name: reditio
Version: 0.2.0
Summary: Simple typed Python interface to Redis
Home-page: https://github.com/MatthewScholefield/reditio
Author: Matthew D. Scholefield
Author-email: matthew331199@gmail.com
Keywords: reditio
Classifier: Development Status :: 3 - Alpha
Classifier: Intended Audience :: Developers
Classifier: Programming Language :: Python :: 3
Classifier: Programming Language :: Python :: 3.8
Classifier: Programming Language :: Python :: 3.9
Classifier: Programming Language :: Python :: 3.10
Provides-Extra: dev
License-File: LICENSE
